mcp_kubernetes_server/__init__.py
mcp_kubernetes_server/auth.py
mcp_kubernetes_server/command.py
mcp_kubernetes_server/copy.py
mcp_kubernetes_server/create.py
mcp_kubernetes_server/describe.py
mcp_kubernetes_server/events.py
mcp_kubernetes_server/get.py
mcp_kubernetes_server/kubeclient.py
mcp_kubernetes_server/logs.py
mcp_kubernetes_server/main.py
mcp_kubernetes_server/port_forward.py
mcp_kubernetes_server/rollout.py
mcp_kubernetes_server/set.py
mcp_kubernetes_server/top.py
mcp_kubernetes_server-0.1.11.dist-info/licenses/LICENSE
mcp_kubernetes_server-0.1.11.dist-info/METADATA
mcp_kubernetes_server-0.1.11.dist-info/WHEEL
mcp_kubernetes_server-0.1.11.dist-info/entry_points.txt
mcp_kubernetes_server-0.1.11.dist-info/top_level.txt
mcp_kubernetes_server-0.1.11.dist-info/RECORD
