Metadata-Version: 2.4
Name: mcp-kubernetes-server
Version: 0.1.11
Summary: The mcp-kubernetes-server is a Model Context Protocol (MCP) server that enables AI assistants to interact with Kubernetes clusters. It serves as a bridge between AI tools (like Claude, Cursor, and GitHub Copilot) and Kubernetes, translating natural language requests into Kubernetes operations and returning the results in a format the AI tools can understand.
Requires-Python: >=3.11
License-File: LICENSE
Requires-Dist: fastmcp>=2.3.3
Requires-Dist: kubernetes>=32.0.1
Dynamic: license-file
